pyproject_tag_check/__init__.py
pyproject_tag_check-1.1.0.dist-info/LICENSE
pyproject_tag_check-1.1.0.dist-info/METADATA
pyproject_tag_check-1.1.0.dist-info/WHEEL
pyproject_tag_check-1.1.0.dist-info/entry_points.txt
pyproject_tag_check-1.1.0.dist-info/RECORD
